video_facenet/__init__.py
video_facenet/align.py
video_facenet/cluster_analysis.py
video_facenet/facenet.py
video_facenet/facenet_encoder.py
video_facenet/facenet_types.py
video_facenet/files.py
video_facenet/hdbscan_clustering.py
video_facenet/pipelines.py
video_facenet/utils.py
video_facenet/video.py
video_facenet-0.1.0.dist-info/METADATA
video_facenet-0.1.0.dist-info/WHEEL
video_facenet-0.1.0.dist-info/top_level.txt
video_facenet-0.1.0.dist-info/RECORD
